mcp_sports_server/__init__.py
mcp_sports_server/main.py
mcp_sports_server/sportsclasses.py
mcp_sports_server-1.0.3.dist-info/METADATA
mcp_sports_server-1.0.3.dist-info/WHEEL
mcp_sports_server-1.0.3.dist-info/entry_points.txt
mcp_sports_server-1.0.3.dist-info/licenses/LICENSE
mcp_sports_server-1.0.3.dist-info/RECORD
