Metadata-Version: 2.3
Name: mcp-sports-server
Version: 1.0.3
Summary: Model Context Protocol SDK for real-time sports stats. Requires an API key from SportsRadar
Project-URL: Repository, https://github.com/reeeeemo/mcp-sports.git
Author: Robert Oxley
Maintainer-email: Robert Oxley <robert@oxley.ca>
License: MIT
Keywords: automation,llm,mcp,sports,stats
Classifier: Development Status :: 5 - Production/Stable
Classifier: Intended Audience :: Developers
Classifier: License :: OSI Approved :: MIT License
Classifier: Programming Language :: Python :: 3
Classifier: Programming Language :: Python :: 3.10
Requires-Python: >=3.10
Requires-Dist: argparse
Requires-Dist: fastapi
Requires-Dist: fastmcp
Requires-Dist: geopy
Requires-Dist: pydantic
Requires-Dist: requests
Requires-Dist: starlette
Requires-Dist: typing-extensions
Requires-Dist: uvicorn
